{
  "schema_version": "1",
  "paper_profile": {
    "title": "Unknown",
    "page_count": 25,
    "input_pdf_sha256": "fcf839b1a1721f92f45ff599715d0fe9d44806fd612395fed1a48dbd094426b7",
    "parser": {
      "name": "docling",
      "version": "2.93.0",
      "config": {
        "do_formula_enrichment": true,
        "do_code_enrichment": false,
        "do_ocr": false
      }
    },
    "tool_version": "0.1.0"
  },
  "sections": [
    {
      "id": "sec-001",
      "heading": "ORIGINAL PAPER",
      "level": 2,
      "start_char": 0,
      "end_char": 19
    },
    {
      "id": "sec-002",
      "heading": "Solving methods for interval linear programming problem: a review and an improved method",
      "level": 2,
      "start_char": 19,
      "end_char": 1986
    },
    {
      "id": "sec-003",
      "heading": "1 Introduction",
      "level": 2,
      "start_char": 1986,
      "end_char": 8959
    },
    {
      "id": "sec-004",
      "heading": "2 Preliminaries",
      "level": 2,
      "start_char": 8959,
      "end_char": 9134
    },
    {
      "id": "sec-005",
      "heading": "2.1 General form of ILP",
      "level": 2,
      "start_char": 9134,
      "end_char": 11186
    },
    {
      "id": "sec-006",
      "heading": "2.2 Basis stability and optimal solution set to the ILP model",
      "level": 2,
      "start_char": 11186,
      "end_char": 15279
    },
    {
      "id": "sec-007",
      "heading": "3 Review of previous solving methods of ILP",
      "level": 2,
      "start_char": 15279,
      "end_char": 15724
    },
    {
      "id": "sec-008",
      "heading": "3.1 BWC method",
      "level": 2,
      "start_char": 15724,
      "end_char": 17111
    },
    {
      "id": "sec-009",
      "heading": "3.2 TSM method",
      "level": 2,
      "start_char": 17111,
      "end_char": 21173
    },
    {
      "id": "sec-010",
      "heading": "3.3 MILP method",
      "level": 2,
      "start_char": 21173,
      "end_char": 25054
    },
    {
      "id": "sec-011",
      "heading": "3.4 ITSM method",
      "level": 2,
      "start_char": 25054,
      "end_char": 32438
    },
    {
      "id": "sec-012",
      "heading": "3.5 ThSM methods",
      "level": 2,
      "start_char": 32438,
      "end_char": 36377
    },
    {
      "id": "sec-013",
      "heading": "3.6 RTSM method",
      "level": 2,
      "start_char": 36377,
      "end_char": 40182
    },
    {
      "id": "sec-014",
      "heading": "3.7 SOM-2 method",
      "level": 2,
      "start_char": 40182,
      "end_char": 43532
    },
    {
      "id": "sec-015",
      "heading": "3.8 IILP method",
      "level": 2,
      "start_char": 43532,
      "end_char": 46760
    },
    {
      "id": "sec-016",
      "heading": "3.9 IMILP method",
      "level": 2,
      "start_char": 46760,
      "end_char": 49410
    },
    {
      "id": "sec-017",
      "heading": "4 Improved method",
      "level": 2,
      "start_char": 49410,
      "end_char": 58615
    },
    {
      "id": "sec-018",
      "heading": "5 Numerical example",
      "level": 2,
      "start_char": 58615,
      "end_char": 69934
    },
    {
      "id": "sec-019",
      "heading": "6 Conclusion",
      "level": 2,
      "start_char": 69934,
      "end_char": 71147
    },
    {
      "id": "sec-020",
      "heading": "References",
      "level": 2,
      "start_char": 71147,
      "end_char": 75841
    }
  ],
  "figures": [
    {
      "id": "fig-001",
      "page": 1,
      "bbox": [
        334.41778564453125,
        617.9006576538086,
        387.0245666503906,
        638.506462097168
      ],
      "caption": null,
      "image_path": "visuals/figures/figure_001.png"
    },
    {
      "id": "fig-002",
      "page": 1,
      "bbox": [
        345.73468017578125,
        30.33551025390625,
        388.4870910644531,
        42.96868896484375
      ],
      "caption": null,
      "image_path": "visuals/figures/figure_002.png"
    },
    {
      "id": "fig-003",
      "page": 2,
      "bbox": [
        49.804420471191406,
        30.49658203125,
        92.44660186767578,
        43.01611328125
      ],
      "caption": null,
      "image_path": "visuals/figures/figure_003.png"
    },
    {
      "id": "fig-004",
      "page": 3,
      "bbox": [
        345.83209228515625,
        30.25787353515625,
        388.5463562011719,
        42.9248046875
      ],
      "caption": null,
      "image_path": "visuals/figures/figure_004.png"
    },
    {
      "id": "fig-005",
      "page": 4,
      "bbox": [
        49.636844635009766,
        30.4188232421875,
        92.35710144042969,
        42.98419189453125
      ],
      "caption": null,
      "image_path": "visuals/figures/figure_005.png"
    },
    {
      "id": "fig-006",
      "page": 5,
      "bbox": [
        345.5332946777344,
        30.3116455078125,
        388.5150146484375,
        43.08648681640625
      ],
      "caption": null,
      "image_path": "visuals/figures/figure_006.png"
    },
    {
      "id": "fig-007",
      "page": 6,
      "bbox": [
        49.7413215637207,
        30.43572998046875,
        92.42774200439453,
        42.940185546875
      ],
      "caption": null,
      "image_path": "visuals/figures/figure_007.png"
    },
    {
      "id": "fig-008",
      "page": 7,
      "bbox": [
        345.6068420410156,
        30.32208251953125,
        388.5052490234375,
        42.97454833984375
      ],
      "caption": null,
      "image_path": "visuals/figures/figure_008.png"
    },
    {
      "id": "fig-009",
      "page": 8,
      "bbox": [
        49.69537353515625,
        30.43621826171875,
        92.4146499633789,
        43.0108642578125
      ],
      "caption": null,
      "image_path": "visuals/figures/figure_009.png"
    },
    {
      "id": "fig-010",
      "page": 9,
      "bbox": [
        345.6363220214844,
        30.303955078125,
        388.50537109375,
        42.943603515625
      ],
      "caption": null,
      "image_path": "visuals/figures/figure_010.png"
    },
    {
      "id": "fig-011",
      "page": 10,
      "bbox": [
        49.716514587402344,
        30.42626953125,
        92.42940521240234,
        43.049560546875
      ],
      "caption": null,
      "image_path": "visuals/figures/figure_011.png"
    },
    {
      "id": "fig-012",
      "page": 11,
      "bbox": [
        345.60809326171875,
        30.33221435546875,
        388.51483154296875,
        42.9168701171875
      ],
      "caption": null,
      "image_path": "visuals/figures/figure_012.png"
    },
    {
      "id": "fig-013",
      "page": 12,
      "bbox": [
        49.69940948486328,
        30.44647216796875,
        92.40728759765625,
        42.9429931640625
      ],
      "caption": null,
      "image_path": "visuals/figures/figure_013.png"
    },
    {
      "id": "fig-014",
      "page": 13,
      "bbox": [
        345.60333251953125,
        30.3048095703125,
        388.49810791015625,
        43.00567626953125
      ],
      "caption": null,
      "image_path": "visuals/figures/figure_014.png"
    },
    {
      "id": "fig-015",
      "page": 14,
      "bbox": [
        49.60094451904297,
        30.44757080078125,
        92.42084503173828,
        43.064697265625
      ],
      "caption": null,
      "image_path": "visuals/figures/figure_015.png"
    },
    {
      "id": "fig-016",
      "page": 15,
      "bbox": [
        345.54925537109375,
        30.2662353515625,
        388.5417175292969,
        43.04461669921875
      ],
      "caption": null,
      "image_path": "visuals/figures/figure_016.png"
    },
    {
      "id": "fig-017",
      "page": 16,
      "bbox": [
        49.69668197631836,
        30.40673828125,
        92.4749755859375,
        42.981689453125
      ],
      "caption": null,
      "image_path": "visuals/figures/figure_017.png"
    },
    {
      "id": "fig-018",
      "page": 17,
      "bbox": [
        345.62188720703125,
        30.28350830078125,
        388.5041809082031,
        42.98681640625
      ],
      "caption": null,
      "image_path": "visuals/figures/figure_018.png"
    },
    {
      "id": "fig-019",
      "page": 18,
      "bbox": [
        49.758949279785156,
        30.3653564453125,
        92.44270324707031,
        42.93524169921875
      ],
      "caption": null,
      "image_path": "visuals/figures/figure_019.png"
    },
    {
      "id": "fig-020",
      "page": 19,
      "bbox": [
        91.4043960571289,
        351.1739807128906,
        346.8900146484375,
        608.5666084289551
      ],
      "caption": "Fig. 1 The feasible region and extreme zones of the ILP model",
      "image_path": "visuals/figures/figure_020.png"
    },
    {
      "id": "fig-021",
      "page": 19,
      "bbox": [
        345.6117248535156,
        30.3419189453125,
        388.49462890625,
        43.00970458984375
      ],
      "caption": null,
      "image_path": "visuals/figures/figure_021.png"
    },
    {
      "id": "fig-022",
      "page": 20,
      "bbox": [
        52.05533218383789,
        89.058837890625,
        385.683837890625,
        251.03585815429688
      ],
      "caption": null,
      "image_path": "visuals/figures/figure_022.png"
    },
    {
      "id": "fig-023",
      "page": 20,
      "bbox": [
        49.67742919921875,
        30.418212890625,
        92.44219207763672,
        43.06488037109375
      ],
      "caption": null,
      "image_path": "visuals/figures/figure_023.png"
    },
    {
      "id": "fig-024",
      "page": 21,
      "bbox": [
        52.23102569580078,
        89.30224609375,
        386.09857177734375,
        254.22088623046875
      ],
      "caption": null,
      "image_path": "visuals/figures/figure_024.png"
    },
    {
      "id": "fig-025",
      "page": 21,
      "bbox": [
        345.7038879394531,
        30.39886474609375,
        388.5751037597656,
        42.9512939453125
      ],
      "caption": null,
      "image_path": "visuals/figures/figure_025.png"
    },
    {
      "id": "fig-026",
      "page": 22,
      "bbox": [
        49.976924896240234,
        30.43267822265625,
        92.38017272949219,
        42.9039306640625
      ],
      "caption": null,
      "image_path": "visuals/figures/figure_026.png"
    },
    {
      "id": "fig-027",
      "page": 23,
      "bbox": [
        91.01671600341797,
        342.1401062011719,
        347.559326171875,
        608.7221527099609
      ],
      "caption": "Fig. 4 The range of optimum objective function values of the ILP model (24) using the solving methods",
      "image_path": "visuals/figures/figure_027.png"
    },
    {
      "id": "fig-028",
      "page": 23,
      "bbox": [
        345.7354736328125,
        30.44671630859375,
        388.5341491699219,
        42.93353271484375
      ],
      "caption": null,
      "image_path": "visuals/figures/figure_028.png"
    },
    {
      "id": "fig-029",
      "page": 24,
      "bbox": [
        49.80573654174805,
        30.3577880859375,
        92.4662857055664,
        42.978515625
      ],
      "caption": null,
      "image_path": "visuals/figures/figure_029.png"
    },
    {
      "id": "fig-030",
      "page": 25,
      "bbox": [
        345.8237609863281,
        30.2781982421875,
        388.521484375,
        42.9227294921875
      ],
      "caption": null,
      "image_path": "visuals/figures/figure_030.png"
    }
  ],
  "tables": [
    {
      "id": "tab-001",
      "page": 21,
      "bbox": [
        165.54928588867188,
        482.99827575683594,
        388.8607177734375,
        608.2446136474609
      ],
      "csv_path": "debug/tables/tab-001.csv",
      "rows": 0,
      "cols": 0
    },
    {
      "id": "tab-002",
      "page": 22,
      "bbox": [
        50.11431884765625,
        76.6221923828125,
        389.015869140625,
        139.26739501953125
      ],
      "csv_path": "debug/tables/tab-002.csv",
      "rows": 0,
      "cols": 0
    }
  ],
  "equations": [
    {
      "id": "eq-001",
      "page": 4,
      "bbox": [
        139.80431139474223,
        379.94965691721893,
        388.32830768026037,
        458.0971330985937
      ],
      "latex": "\\text {from of ILP model is considered as follows:} \\\\ \\max f ^ { \\pm } = \\sum _ { j = 1 } ^ { n } c _ { j } ^ { \\pm } x _ { j } ^ { \\pm } \\\\ s . t. \\quad \\sum _ { j = 1 } ^ { n } a _ { i j } ^ { \\pm } x _ { j } ^ { \\pm } \\leq b _ { i } ^ { \\pm } , \\ i = 1 , \\dots , m , \\\\ x _ { j } ^ { \\pm } \\geq 0 , \\ j = 1 , \\dots , n . \\\\ \\intertext { s . t. } \\text {characteristic model of ILP model (1) can be expressed as follows:}",
      "image_path": "visuals/equations/equation_001.png",
      "number": null
    },
    {
      "id": "eq-002",
      "page": 4,
      "bbox": [
        145.30660933674903,
        276.88200445421893,
        388.32820645365274,
        352.1381182085937
      ],
      "latex": "\\text {characterize model of linear} \\, ( 1 ) \\, \\text {can be express as} \\, 3 \\text { in} \\, 0 \\text {s.} \\\\ \\max f = \\sum _ { j = 1 } ^ { n } c _ { j } x _ { j } \\\\ s . t. \\quad \\sum _ { j = 1 } ^ { n } a _ { i j } x _ { j } \\leq b _ { i } , \\ i = 1 , \\dots , m , \\\\ x _ { j } \\geq 0 , \\ j = 1 , \\dots , n . \\\\ \\# = [ \\sigma _ { j } + ] _ { \\ } a _ { j } \\subset \\# + ] _ { \\ } a _ { j } \\oplus \\# + ] _ { \\ } a _ { j } \\subset h \\neq - \\ [ \\sigma _ { j } ^ { - } + ] _ { \\ } a _ { j }",
      "image_path": "visuals/equations/equation_002.png",
      "number": null
    },
    {
      "id": "eq-003",
      "page": 5,
      "bbox": [
        83.67895697453613,
        98.97969122221889,
        355.6597454046074,
        149.8015686737417
      ],
      "latex": "r _ { i } ^ { - } & = \\min \\{ - x _ { i } ^ { * } + ( x _ { i } ^ { c } + | x _ { i } ^ { c } | ) M _ { i i } , \\frac { 1 } { 2 M _ { i i } - 1 } ( - x _ { i } ^ { * } + ( x _ { i } ^ { c } + | x _ { i } ^ { c } | ) M _ { i i } ) \\} , \\\\ r _ { i } ^ { + } & = \\max \\{ x _ { i } ^ { * } + ( x _ { i } ^ { c } - | x _ { i } ^ { c } | ) M _ { i i } , \\frac { 1 } { 2 M _ { i i } - 1 } ( x _ { i } ^ { * } + ( x _ { i } ^ { c } - | x _ { i } ^ { c } | ) M _ { i i } ) \\} ,",
      "image_path": "visuals/equations/equation_003.png",
      "number": null
    },
    {
      "id": "eq-004",
      "page": 6,
      "bbox": [
        137.3683607645787,
        489.77968957631833,
        300.32759724558,
        532.4782366145937
      ],
      "latex": "\\begin{cases} & ( ( A _ { B } ^ { c } ) ^ { T } - ( \\triangle _ { A _ { B } } ) ^ { T } d i a g ( q ) ) y \\leq \\mathfrak { c } _ { B } ^ { + } , \\\\ & - ( ( A _ { B } ^ { c } ) ^ { T } + ( \\triangle _ { A _ { B } } ) ^ { T } d i a g ( q ) ) y \\leq - \\mathfrak { c } _ { B } ^ { - } , \\\\ & d i a g ( q ) y \\geq 0 , \\end{cases}",
      "image_path": "visuals/equations/equation_004.png",
      "number": null
    },
    {
      "id": "eq-005",
      "page": 6,
      "bbox": [
        156.6439943551862,
        433.25697810391614,
        290.68981038058,
        459.9113115655937
      ],
      "latex": "\\begin{cases} \\left ( ( A _ { N } ^ { c } ) ^ { T } - ( \\triangle _ { A _ { N } } ) ^ { T } d i a g ( q ) \\right ) y \\geq \\mathfrak { c } _ { N } ^ { + } , \\\\ d i a g ( q ) y \\geq 0 , \\end{cases}",
      "image_path": "visuals/equations/equation_005.png",
      "number": null
    },
    {
      "id": "eq-006",
      "page": 6,
      "bbox": [
        141.50492643551755,
        95.46469183221893,
        388.32836673307395,
        170.7208202085937
      ],
      "latex": "\\text {sub-model} . & & \\max Z ^ { + } = \\sum _ { j = 1 } ^ { n } c _ { j } ^ { + } x _ { j } \\\\ & & s . t . \\quad \\sum _ { j = 1 } ^ { n } a _ { i j } ^ { - } x _ { j } \\leq b _ { i } ^ { + } , \\ i = 1 , \\dots , m , \\\\ & & x _ { j } \\geq 0 , \\ j = 1 , \\dots , n .",
      "image_path": "visuals/equations/equation_006.png",
      "number": null
    },
    {
      "id": "eq-007",
      "page": 7,
      "bbox": [
        141.5049287568034,
        514.0850989362189,
        388.32836673307395,
        589.3412126885937
      ],
      "latex": "\\max Z ^ { - } & = \\sum _ { j = 1 } ^ { n } c _ { j } ^ { - } x _ { j } \\\\ s . t . & \\quad \\sum _ { j = 1 } ^ { n } a _ { i j } ^ { + } x _ { j } \\leq b _ { i } ^ { - } , \\ i = 1 , \\dots , m , \\\\ x _ { j } & \\geq 0 , \\ j = 1 , \\dots , n .",
      "image_path": "visuals/equations/equation_007.png",
      "number": null
    },
    {
      "id": "eq-008",
      "page": 7,
      "bbox": [
        62.305954652654634,
        141.55605645321884,
        388.3262715693344,
        221.45374987759368
      ],
      "latex": "\\max & Z ^ { + } = \\sum _ { j \\in A _ { 1 } } c _ { j } ^ { + } x _ { j } ^ { + } + \\sum _ { j \\in A _ { 2 } } c _ { j } ^ { + } x _ { j } ^ { - } \\\\ & s . t . \\quad \\sum _ { j \\in A _ { 1 } } | a _ { i j } ^ { + } | ^ { - } s i g n ( a _ { i j } ^ { + } ) x _ { j } ^ { + } + \\sum _ { j \\in A _ { 2 } } | a _ { i j } ^ { + } | ^ { + } s i g n ( a _ { i j } ^ { + } ) x _ { j } ^ { - } \\leq b _ { i } ^ { + } , \\ i = 1 , \\dots , m , \\quad ( 5 ) \\\\ & x _ { j } ^ { + } \\geq 0 , \\ \\text { for } j \\in A _ { 1 } , \\\\ & x _ { j } ^ { - } \\geq 0 , \\ \\text { for } j \\in A _ { 2 } . \\\\ \\text { Solving the model (5) the optimal solutions and optimum objective function value}",
      "image_path": "visuals/equations/equation_008.png",
      "number": null
    },
    {
      "id": "eq-009",
      "page": 8,
      "bbox": [
        62.3055,
        524.0567359124962,
        388.3263350972053,
        606.3419182125938
      ],
      "latex": "\\max & Z ^ { - } = \\sum _ { j \\in A _ { 1 } } c _ { j } ^ { - } \\, x _ { j } ^ { - } + \\sum _ { j \\in A _ { 2 } } c _ { j } ^ { - } \\, x _ { j } ^ { + } \\\\ & s . t . \\quad \\sum _ { j \\in A _ { 1 } } | a _ { i j } ^ { \\pm } | ^ { + } s i g n ( a _ { i j } ^ { \\pm } ) x _ { j } ^ { - } + \\sum | a _ { i j } ^ { \\pm } | ^ { - } s i g n ( a _ { i j } ^ { \\pm } ) x _ { j } ^ { + } \\leq b _ { i } ^ { - } , \\ i = 1 , \\dots , m , \\\\ & 0 \\leq x _ { j } ^ { - } \\leq x _ { j _ { o p t } } ^ { + } , \\ \\text {for} \\ j \\in A _ { 1 } , \\\\ & x _ { j } ^ { + } \\geq x _ { j _ { o p t } } ^ { - } , \\quad \\text {for} \\ j \\in A _ { 2 } , \\\\ & \\quad \\left ( \\int _ { 0 } ^ { a _ { j } ^ { - } } \\int _ { x _ { j _ { o p t } } } ^ { a _ { j } ^ { + } > 0 } \\left ( \\int _ { 0 } ^ { a _ { j } ^ { + } } \\int _ { x _ { j } ^ { - } } ^ { a _ { j } ^ { + } > 0 } \\right )",
      "image_path": "visuals/equations/equation_009.png",
      "number": null
    },
    {
      "id": "eq-010",
      "page": 8,
      "bbox": [
        51.02374821765878,
        460.4537770472189,
        388.3073283611954,
        515.5198356935937
      ],
      "latex": "& \\text {where} \\quad | a _ { i j } ^ { \\pm } | ^ { - } = \\begin{cases} \\ a _ { i j } ^ { \\pm } , \\ a _ { i j } ^ { \\pm } \\geq 0 \\\\ - a _ { i j } ^ { \\pm } , \\ a _ { i j } ^ { \\pm } < 0 \\end{cases} , \\quad | a _ { i j } ^ { \\pm } | ^ { + } = \\begin{cases} \\ a _ { i j } ^ { + } , \\ a _ { i j } ^ { \\pm } \\geq 0 \\\\ - a _ { i j } ^ { - } , \\ a _ { i j } ^ { \\pm } < 0 \\end{cases} , \\quad \\text {and} \\quad \\ s i g n ( a _ { i j } ^ { \\pm } ) = \\\\ & \\quad \\left \\{ \\begin{array} { l l } { 1 , \\ a _ { i j } ^ { \\pm } \\geq 0 } \\\\ { - 1 , \\ a _ { i j } ^ { \\pm } < 0 } \\\\ { \\text {By solving this sub-model the optimal solutions are } x _ { i } ^ { - } , \\text { for } j \\in A _ { 1 } \\text { and} } \\end{array}",
      "image_path": "visuals/equations/equation_010.png",
      "number": null
    },
    {
      "id": "eq-011",
      "page": 8,
      "bbox": [
        98.305496215,
        84.7287198481024,
        388.3266358886265,
        107.21754340859366
      ],
      "latex": "\\sum _ { j \\in B _ { 2 } } - ( | a _ { \\delta j } ^ { \\pm } | ^ { + } x _ { j } ^ { - } - | a _ { \\delta j } ^ { \\pm } | ^ { - } x _ { j _ { \\rho \\rho } } ^ { + } ) + \\sum _ { j \\in B _ { 4 } } ( | a _ { \\delta j } ^ { \\pm } | ^ { - } x _ { j } ^ { + } - | a _ { \\delta j } ^ { \\pm } | ^ { + } x _ { j _ { \\rho \\rho } } ^ { - } ) \\leq 0 \\\\",
      "image_path": "visuals/equations/equation_011.png",
      "number": null
    },
    {
      "id": "eq-012",
      "page": 9,
      "bbox": [
        113.0456,
        584.3632108141023,
        326.57640705958,
        607.0222160645937
      ],
      "latex": "\\sum _ { j \\in A _ { 1 } } | a _ { \\delta j } ^ { \\pm } | ^ { - } s i g n ( a _ { \\delta j } ^ { \\pm } ) x _ { j _ { o p t } } ^ { + } + \\sum _ { j \\in A _ { 2 } } | a _ { \\delta j } ^ { \\pm } | ^ { + } s i g n ( a _ { \\delta j } ^ { \\pm } ) x _ { j _ { o p t } } ^ { - } = b _ { \\delta } ^ { + } .",
      "image_path": "visuals/equations/equation_012.png",
      "number": null
    },
    {
      "id": "eq-013",
      "page": 9,
      "bbox": [
        92.125834838,
        497.45302404710236,
        348.97011433558004,
        526.3554338795936
      ],
      "latex": "\\sum _ { j = 1 } ^ { n } a _ { \\delta j } ^ { - } x _ { j } \\leq b _ { \\delta } ^ { + } = \\sum _ { j \\in A _ { 1 } } | a _ { \\delta j } ^ { \\pm } | ^ { - } s i g n ( a _ { \\delta j } ^ { \\pm } ) x _ { j _ { \\rho \\mu } } ^ { + } + \\sum _ { j \\in A _ { 2 } } | a _ { \\delta j } ^ { \\pm } | ^ { + } s i g n ( a _ { \\delta j } ^ { \\pm } ) x _ { j _ { \\rho \\mu } } ^ { - } .",
      "image_path": "visuals/equations/equation_013.png",
      "number": null
    },
    {
      "id": "eq-014",
      "page": 9,
      "bbox": [
        62.30627350711653,
        337.5790311271024,
        388.32770327279553,
        446.0710434085937
      ],
      "latex": "\\text { Therefore, the second sub-model is as follows:} \\\\ \\max Z ^ { - } = \\sum _ { j \\in A _ { 1 } } c _ { j } ^ { - } x _ { j } ^ { - } + \\sum _ { j \\in A _ { 2 } } c _ { j } ^ { + } x _ { j } ^ { + } \\\\ s . t. \\sum _ { j \\in A _ { 1 } } | a _ { j } ^ { + } | ^ { + } s i g n ( a _ { i j } ^ { \\pm } ) x _ { j } ^ { - } + \\sum _ { j \\in A _ { 2 } } | a _ { i j } ^ { + } | ^ { - } s i g n ( a _ { i j } ^ { + } ) x _ { j } ^ { + } \\leq b _ { i } ^ { - } , \\ i = 1 , \\dots , m , \\\\ 0 \\leq x _ { j } ^ { - } \\leq x _ { j _ { o p t } } ^ { + } , \\ \\text { for } j \\in A _ { 1 } , \\\\ x _ { j } ^ { + } \\geq x _ { j _ { o p t } } ^ { - } , \\quad \\text { for } j \\in A _ { 2 } , \\\\ \\sum _ { j \\in B _ { 2 } } ( | a _ { \\delta j } ^ { + } | ^ { + } x _ { j } ^ { - } - | a _ { \\delta j } ^ { + } | ^ { - } x _ { j _ { o p t } } ^ { + } ) + \\sum _ { j \\in B _ { 4 } } ( | a _ { \\delta j } ^ { + } | ^ { - } x _ { j } ^ { + } - | a _ { \\delta j } ^ { + } | ^ { + } x _ { j _ { o p t } } ^ { - } ) \\leq 0 . \\\\ \\text {By solving sub-models } ( 5 ) \\text { and } ( 8 ) \\text { and combining their optimal solutions, the}",
      "image_path": "visuals/equations/equation_014.png",
      "number": null
    },
    {
      "id": "eq-015",
      "page": 10,
      "bbox": [
        54.651901245,
        441.3641064597101,
        388.3268222149029,
        606.3419182125938
      ],
      "latex": "\\frac { 1 2 1 4 } { \\max Z ^ { - } & = \\sum _ { j A _ { 1 } } c _ { j } ^ { - } x _ { j } ^ { - } + \\sum _ { j E A _ { 2 } } c _ { j } ^ { - } x _ { j } ^ { + } \\\\ s . t . & \\sum _ { j E A _ { 1 } } | a _ { i j } ^ { + } | ^ { * } s i g n ( a _ { i j } ^ { + } ) x _ { j } ^ { - } + \\sum _ { j \\in A _ { 2 } } | a _ { i j } ^ { + } | ^ { * } s i g n ( a _ { i j } ^ { + } ) x _ { j } ^ { + } \\leq b _ { i } ^ { - } , \\ i = 1 , \\dots , m , \\\\ & \\quad \\quad \\quad \\quad \\quad \\quad \\quad \\quad \\quad \\quad \\quad \\quad \\quad \\quad \\quad \\quad \\quad \\quad \\quad \\quad \\quad \\quad \\quad \\quad \\quad \\quad \\quad \\quad \\quad \\quad \\quad \\quad \\quad \\quad \\quad \\quad \\quad \\quad \\quad \\quad \\quad \\quad \\quad \\quad \\quad \\quad \\quad \\quad \\quad \\quad \\quad \\quad \\quad \\quad \\quad \\quad \\quad \\quad \\quad \\quad \\quad \\quad \\quad \\quad \\quad \\quad \\quad \\quad \\quad \\quad \\quad \\quad \\quad \\quad \\quad \\quad \\quad \\quad \\quad \\quad \\quad \\quad \\quad \\quad \\quad \\quad \\quad \\quad \\quad \\quad \\quad \\quad \\quad \\quad \\quad \\quad \\quad \\quad \\quad \\quad \\quad \\quad \\quad \\quad \\quad \\quad \\quad \\quad \\quad \\quad \\quad \\quad \\quad \\quad \\quad \\quad \\quad \\quad \\quad \\quad \\quad \\quad \\quad \\quad \\quad \\quad \\quad \\quad \\quad \\quad \\quad \\quad \\quad \\quad \\quad \\quad \\quad \\quad \\quad \\quad \\quad \\quad \\quad \\quad \\quad \\quad \\quad \\quad \\quad \\quad \\quad \\quad \\quad \\quad \\quad \\quad \\quad \\quad \\quad \\quad \\quad \\quad \\quad \\quad \\quad \\quad \\quad \\quad \\quad \\quad \\quad \\quad \\quad \\quad \\quad \\quad \\quad \\quad \\quad \\quad \\quad \\quad \\quad \\quad \\quad \\quad \\quad \\quad \\quad \\quad \\quad \\quad \\quad \\quad \\quad \\quad \\quad \\quad \\quad \\quad \\quad \\quad \\quad \\quad \\quad \\quad \\quad \\quad \\quad \\quad \\quad \\quad \\quad \\quad \\quad \\quad \\quad \\quad \\quad \\quad \\quad \\quad \\quad \\quad \\quad \\quad \\quad \\quad \\quad \\quad \\quad \\quad \\quad \\quad \\quad \\quad \\quad \\quad \\quad \\quad \\quad \\quad \\quad \\quad \\quad \\quad \\quad \\quad \\quad \\quad \\quad \\quad \\quad \\quad \\quad \\quad \\quad \\quad \\quad \\quad \\quad \\quad \\quad \\quad \\quad \\quad \\quad \\quad \\quad \\quad \\quad \\quad \\quad \\quad \\quad \\quad \\quad \\quad \\quad \\quad \\quad \\quad \\quad \\quad \\quad \\quad \\quad \\quad \\quad \\quad \\quad \\quad \\quad \\quad \\quad \\quad \\quad \\quad \\quad \\quad \\quad \\quad \\quad \\quad \\quad \\quad \\quad \\quad \\quad \\quad \\quad \\quad \\quad \\quad \\quad \\quad \\quad \\quad \\quad \\quad \\quad \\quad \\quad \\quad \\quad \\quad \\quad \\quad \\quad \\quad \\quad \\quad \\quad \\quad \\quad \\quad \\quad \\quad \\quad \\quad \\quad \\quad \\quad \\quad \\quad \\quad \\quad \\quad \\quad \\quad \\quad \\quad \\quad \\quad \\quad \\quad \\quad \\quad \\quad \\quad \\quad \\quad \\quad \\quad \\quad \\quad \\quad \\quad \\quad \\quad \\quad \\quad \\quad \\quad \\quad \\quad \\quad \\quad \\quad \\quad \\quad \\quad \\quad \\quad \\quad \\quad \\quad \\quad \\quad \\quad \\quad \\quad \\quad \\quad \\quad \\quad \\quad \\quad \\quad \\quad \\quad \\quad \\quad \\quad \\quad \\quad \\quad \\quad \\quad \\quad \\quad \\quad \\quad \\quad \\quad \\quad \\quad \\quad \\quad \\quad \\quad \\quad \\quad \\quad \\quad \\quad \\quad \\quad \\quad \\quad \\quad \\quad \\quad \\quad \\quad \\quad \\quad \\quad \\quad \\quad \\quad \\quad \\quad \\quad \\quad \\quad \\quad \\quad \\quad \\quad \\quad \\quad \\quad \\quad \\quad \\quad \\quad \\quad \\quad \\quad \\quad \\quad \\quad \\quad \\quad \\quad \\quad \\quad \\quad \\quad \\quad \\quad \\quad \\quad \\quad \\quad \\quad \\quad \\quad \\quad \\quad \\quad \\quad \\quad \\quad \\quad \\quad \\quad \\quad \\quad \\quad \\quad \\quad \\quad \\quad \\quad \\quad \\quad \\quad \\quad \\quad \\quad \\quad \\quad \\quad \\quad \\quad \\quad \\quad \\quad \\quad \\quad \\quad \\quad \\quad \\quad \\quad \\quad \\quad \\quad \\quad \\quad \\quad \\quad \\quad \\quad \\quad \\quad \\quad \\quad \\quad \\quad \\quad \\quad \\quad \\quad \\quad \\quad \\quad \\quad \\quad \\quad \\quad \\quad \\quad \\quad \\quad \\quad \\quad \\quad \\quad \\quad \\quad \\quad \\quad \\quad \\quad \\quad \\quad \\quad \\quad \\quad \\quad \\quad \\quad \\quad \\quad \\quad \\quad \\quad \\quad \\quad \\quad \\quad \\quad \\quad \\quad \\quad \\quad \\quad \\quad \\quad \\quad \\quad \\quad \\quad \\quad \\quad \\quad \\quad \\quad \\quad \\quad \\quad \\quad \\quad \\quad \\quad \\quad \\quad \\quad \\quad \\quad \\quad \\quad \\quad \\quad \\quad \\quad \\quad \\quad \\quad \\quad \\quad \\quad \\quad \\quad \\quad \\quad \\quad \\quad \\quad \\quad \\quad \\quad \\quad \\quad \\quad \\quad \\quad \\quad \\quad \\quad \\quad \\quad \\quad \\quad \\quad \\quad \\quad \\quad \\quad \\quad \\quad \\quad \\quad \\quad \\quad \\quad \\quad \\quad \\quad \\quad \\quad \\quad \\quad \\quad \\quad \\quad \\quad \\quad \\quad \\quad \\quad \\quad \\quad \\quad \\quad \\quad \\quad \\quad \\quad \\quad \\quad \\quad \\quad \\quad \\quad \\quad \\quad \\quad \\quad \\quad \\quad \\quad \\quad \\quad \\quad \\quad \\quad \\quad \\quad \\quad \\quad \\quad \\quad \\quad \\quad \\quad \\quad \\quad \\quad \\quad \\quad \\quad \\quad \\quad \\quad \\quad \\quad \\quad \\quad \\quad \\quad \\quad \\quad \\quad \\quad \\quad \\quad \\quad \\quad \\quad \\quad \\quad \\quad \\quad \\quad \\quad \\quad \\quad \\quad \\quad \\quad \\quad \\quad \\quad \\quad \\quad \\quad \\quad \\quad \\quad \\quad \\quad \\quad \\quad \\quad \\quad \\quad \\quad \\quad \\quad \\quad \\quad \\quad \\quad \\quad \\quad \\quad \\quad \\quad \\quad \\quad \\quad \\quad \\quad \\quad \\quad \\quad \\quad \\quad \\quad \\quad \\quad \\quad \\quad \\quad \\quad \\quad \\quad \\quad \\quad \\quad \\quad \\quad \\quad \\quad \\quad \\quad \\quad \\quad \\quad \\quad \\quad \\quad \\quad \\quad \\quad \\quad \\quad \\quad \\quad \\quad \\quad \\quad \\quad \\quad \\quad \\quad \\quad \\quad \\quad \\quad \\quad \\quad \\quad \\quad \\quad \\quad \\quad \\quad \\quad \\quad \\quad \\quad \\quad \\quad \\quad \\quad \\quad \\quad \\quad \\quad \\quad \\quad \\quad \\quad \\quad \\quad \\quad \\quad \\quad \\quad \\quad \\quad \\quad \\quad \\quad \\quad \\quad \\quad \\quad \\quad \\quad \\quad \\quad \\quad \\quad \\quad \\quad \\quad \\quad \\quad \\quad \\quad \\quad \\quad \\quad \\quad \\quad \\quad \\quad \\quad \\quad \\quad \\quad \\quad \\quad \\quad \\quad \\quad \\quad \\quad \\quad \\quad \\quad \\quad \\quad \\quad \\quad \\quad \\quad \\quad \\quad \\quad \\quad \\quad \\quad \\quad \\quad \\quad \\quad \\quad \\qu",
      "image_path": "visuals/equations/equation_015.png",
      "number": null
    },
    {
      "id": "eq-016",
      "page": 10,
      "bbox": [
        84.69959437317242,
        94.32451242049615,
        354.63939534158004,
        124.25151750190787
      ],
      "latex": "A ^ { - } y _ { o p t } ^ { \\pm } = \\sum _ { j = 1 } ^ { p _ { i } } a _ { i j } ^ { - } ( m _ { j } + q d _ { j } ) + \\sum _ { j = p _ { i } + 1 } ^ { n _ { 0 } } a _ { i j } ^ { - } ( m _ { j } - q d _ { j } ) + \\sum _ { j = n _ { 0 } } ^ { n } a _ { i j } ^ { - } m _ { j } \\leq b _ { i } ^ { + } .",
      "image_path": "visuals/equations/equation_016.png",
      "number": null
    },
    {
      "id": "eq-017",
      "page": 11,
      "bbox": [
        104.93849945,
        577.9148902284962,
        334.40183116585763,
        607.8422788646817
      ],
      "latex": "\\sum _ { j = 1 } ^ { p _ { i } } a _ { i j } ^ { - } q d _ { j } - \\sum _ { j = p _ { i } + 1 } ^ { n _ { 0 } } a _ { i j } ^ { - } q d _ { j } \\leq b _ { i } ^ { + } - \\sum _ { j = 1 } ^ { n } a _ { i j } ^ { - } m _ { j } , \\ i = 1 , \\dots , m .",
      "image_path": "visuals/equations/equation_017.png",
      "number": null
    },
    {
      "id": "eq-018",
      "page": 11,
      "bbox": [
        92.86457659409407,
        471.18487630029034,
        388.3277330489755,
        525.8457219235862
      ],
      "latex": "\\max _ { \\ } q & & \\max _ { \\ } q & & \\max _ { \\ } q & & \\max _ { j = p _ { i j } + 1 } ^ { n _ { 0 } } a _ { i j } ^ { - } q d _ { j } \\leq b _ { i } ^ { + } - \\sum _ { j = 1 } ^ { n } a _ { i j } ^ { - } m _ { j } , \\ i = 1 , \\dots , m , \\quad ( 1 0 ) \\\\ s . t . & \\sum _ { j = 1 } ^ { p _ { i } } a _ { i j } ^ { - } q d _ { j } - \\sum _ { j = p _ { i } + 1 } ^ { n _ { 0 } } a _ { i j } ^ { - } q d _ { j } \\leq b _ { i } ^ { + } - \\sum _ { j = 1 } ^ { n } a _ { i j } ^ { - } m _ { j } , \\ i = 1 , \\dots , m , \\quad ( 1 0 ) \\\\ & 0 \\leq q \\leq 1 ,",
      "image_path": "visuals/equations/equation_018.png",
      "number": null
    },
    {
      "id": "eq-019",
      "page": 11,
      "bbox": [
        99.15720509765444,
        376.8672086171024,
        194.8496434685,
        387.6093078022117
      ],
      "latex": "\\max q _ { 1 } \\times q _ { 2 } \\times \\cdots \\times q _ { n _ { 0 } }",
      "image_path": "visuals/equations/equation_019.png",
      "number": null
    },
    {
      "id": "eq-020",
      "page": 11,
      "bbox": [
        90.8787,
        318.8481545352467,
        388.3264827452182,
        372.31045757380565
      ],
      "latex": "s . \\, t . & & s . \\, t . & & \\sum _ { j = 1 } ^ { p _ { i } } a _ { i j } ^ { \\bar { q } } q _ { j } d _ { - } - \\sum _ { j = p _ { i } + 1 } ^ { n _ { 0 } } a _ { i j } ^ { \\bar { q } } q _ { j } d _ { j } \\leq b _ { i } ^ { + } - \\sum _ { j = 1 } ^ { n } a _ { i j } ^ { \\bar { q } } m _ { j } , \\ i = 1 , \\dots , m , \\\\ & & 0 \\leq q _ { j } \\leq 1 , \\ j = 1 , \\dots , n _ { 0 } ,",
      "image_path": "visuals/equations/equation_020.png",
      "number": null
    },
    {
      "id": "eq-021",
      "page": 12,
      "bbox": [
        127.729103088,
        553.3522244861024,
        350.55751667958003,
        575.2174675295937
      ],
      "latex": "\\sum _ { j \\in B _ { 1 } } a _ { i _ { j } j } ^ { - } x _ { j } ^ { + } + \\sum _ { j \\in B _ { 2 } } a _ { i _ { o } j } ^ { - } x _ { j _ { o p } } ^ { - } + \\sum _ { j \\in B _ { 3 } } a _ { i _ { o } j } ^ { - } x _ { j } ^ { - } + \\sum _ { j \\in B _ { 4 } } a _ { i _ { o } j } ^ { - } x _ { j _ { o p } } ^ { + } \\leq b _ { i _ { o } } ^ { + } .",
      "image_path": "visuals/equations/equation_021.png",
      "number": null
    },
    {
      "id": "eq-022",
      "page": 12,
      "bbox": [
        61.45599825230381,
        382.7840539082189,
        388.32641070674333,
        464.7796318355937
      ],
      "latex": "\\text {Sub-Model} \\colon & \\quad I . \\\\ & \\max Z ^ { - } = \\sum _ { j \\in A _ { 1 } } c _ { j } ^ { - } x _ { j } ^ { - } + \\sum _ { j \\in A _ { 2 } } c _ { j } ^ { - } x _ { j } ^ { + } \\\\ & \\quad s . t . \\quad \\sum | a _ { i j } ^ { + } | ^ { + } s i g n ( a _ { i j } ^ { + } ) x _ { j } ^ { - } + \\sum | a _ { i j } ^ { + } | ^ { - } s i g n ( a _ { i j } ^ { + } ) x _ { j } ^ { + } \\leq b _ { i } ^ { - } , \\ i = 1 , \\dots , m , \\\\ & \\quad x _ { j } ^ { - } \\geq 0 , \\ \\text {for} \\ j \\in A _ { 1 } , \\\\ & \\quad x _ { j } ^ { + } \\geq 0 , \\ \\text {for} \\ j \\in A _ { 2 } . \\\\ & \\text {The optimal solution to sub-model} \\ 1 \\text { are } x ^ { - } _ { j } \\text { for } i \\in A _ { j } \\text { and } x ^ { + } _ { j } \\text { for } i \\in A _ { 2 } \\text { and its}",
      "image_path": "visuals/equations/equation_022.png",
      "number": null
    },
    {
      "id": "eq-023",
      "page": 12,
      "bbox": [
        61.45581404538218,
        182.7149776272189,
        388.32643819128054,
        325.7120354085937
      ],
      "latex": "as \\text { follows: } \\\\ \\max Z ^ { + } = \\sum _ { j \\in A _ { 1 } } c _ { j } ^ { + } x _ { j } ^ { + } + \\sum _ { j \\in A _ { 2 } } c _ { j } ^ { + } x _ { j } ^ { - } \\\\ s . t . \\sum _ { j \\in A _ { 1 } } | a _ { i j } ^ { + } | ^ { - } s i g n ( a _ { i j } ^ { + } ) x _ { j } ^ { + } + \\sum _ { j \\in A _ { 2 } } | a _ { i j } ^ { + } | ^ { + } s i g n ( a _ { i j } ^ { + } ) x _ { j } ^ { - } \\leq b _ { i } ^ { + } , \\ i = 1 , \\dots , m , \\\\ \\sum _ { j \\in B _ { 1 } } a _ { i j } ^ { - } x _ { j } ^ { + } + \\sum _ { j \\in B _ { 2 } } a _ { i j } ^ { - } x _ { j } ^ { - } + \\sum _ { j \\in B _ { 3 } } a _ { i j } ^ { - } x _ { j } ^ { + } + \\sum _ { j \\in B _ { 4 } } a _ { i j } ^ { - } x _ { j } ^ { + } \\leq b _ { i } ^ { + } , \\\\ x _ { j } ^ { + } \\geq x _ { j \\text { opt} } ^ { - } , \\text { for } j \\in A _ { 1 } , \\\\ x _ { j } ^ { - } \\leq x _ { j \\text { opt} } ^ { + } , \\text { for } j \\in A _ { 2 } , \\\\ x _ { j } ^ { + } \\geq 0 , \\quad \\text {for } j \\in A _ { 1 } , \\\\ x _ { j } ^ { - } \\geq 0 , \\quad \\text {for } j \\in A _ { 2 } , \\\\ \\text {where } A _ { j } , \\ j = 1 , 2 \\text { and } B _ { j } , \\ j = 1 , \\dots , 4 \\text { are defined in the Subsections 3.2 and 3.3} .",
      "image_path": "visuals/equations/equation_023.png",
      "number": null
    },
    {
      "id": "eq-024",
      "page": 13,
      "bbox": [
        61.456515008833016,
        352.1698571302189,
        388.3257332468131,
        434.16555712859366
      ],
      "latex": "\\text {Sub-Model} \\colon & \\quad I ^ { + } \\colon \\\\ & \\max Z ^ { - } = \\sum _ { j \\in A _ { 1 } } c _ { j } ^ { - } x _ { j } ^ { - } + \\sum _ { j \\in A _ { 2 } } c _ { j } ^ { - } x _ { j } ^ { + } \\\\ & \\quad s . t . \\quad \\sum | a _ { i j } ^ { \\pm } | ^ { + } s i g n ( a _ { i j } ^ { \\pm } ) x _ { j } ^ { - } + \\sum | a _ { i j } ^ { \\pm } | ^ { - } s i g n ( a _ { i j } ^ { \\pm } ) x _ { j } ^ { + } \\leq b _ { i } ^ { + } , \\ i = 1 , \\dots , m , \\\\ & \\quad \\stackrel { - } { x _ { j } ^ { - } } \\geq 0 , \\ \\text {for} \\ j \\in A _ { 1 } , \\\\ & \\quad x _ { j } ^ { + } \\geq 0 , \\ \\text {for} \\ j \\in A _ { 2 } . \\\\ & \\quad \\text {By solving above, sub-model} \\quad \\text {the} \\ \\text {optional} \\ \\text {solutions} \\ \\text {are} \\ \\ r ^ { - } \\ \\text { for} \\ i \\in A _ { i } \\ \\text { and}",
      "image_path": "visuals/equations/equation_024.png",
      "number": null
    },
    {
      "id": "eq-025",
      "page": 13,
      "bbox": [
        61.456639892912264,
        211.16861337249622,
        388.3259619586954,
        294.5309434085937
      ],
      "latex": "0 & \\text { for the first sub-model, } \\text { since second sub-model can be formalized as follows.} \\\\ & \\max Z ^ { + } = \\sum _ { j \\in A _ { 1 } } c _ { j } ^ { + } x _ { j } ^ { + } + \\sum _ { j \\in A _ { 2 } } c _ { j } ^ { + } x _ { j } ^ { - } \\\\ & \\text { s.t. } \\sum | a _ { i j } ^ { \\pm } | ^ { - } s i g n ( a _ { i j } ^ { \\pm } ) x _ { j } ^ { + } + \\sum | a _ { i j } ^ { + } | ^ { + } s i g n ( a _ { i j } ^ { \\pm } ) x _ { j } ^ { - } \\leq b _ { i } ^ { - } , \\ i = 1 , \\dots , m , \\\\ & \\quad x _ { j } ^ { + } \\geq x _ { j _ { o p t } } ^ { - } , \\quad \\text {for } j \\in A _ { 1 } , \\\\ & 0 \\leq x _ { j } ^ { - } \\leq x _ { j _ { o p t } } ^ { + } , \\ \\text { for } j \\in A _ { 2 } . \\\\ & \\text {By combining the solutions of the above, sub-models, final results are:}",
      "image_path": "visuals/equations/equation_025.png",
      "number": null
    },
    {
      "id": "eq-026",
      "page": 14,
      "bbox": [
        61.4567827479356,
        412.0375634292189,
        388.32641070674333,
        494.03323290959366
      ],
      "latex": "\\text {the first sub-model is formulated as follows.} \\\\ \\max Z ^ { - } = \\sum _ { j \\in A _ { 1 } } c _ { j } ^ { - } x _ { j } ^ { - } + \\sum _ { j \\in A _ { 2 } } c _ { j } ^ { - } x _ { j } ^ { + } \\\\ s . t. \\quad \\sum | a _ { i j } ^ { \\pm } | ^ { + } s i g n ( a _ { i j } ^ { \\pm } ) x _ { j } ^ { - } + \\sum | a _ { i j } ^ { \\pm } | ^ { - } s i g n ( a _ { i j } ^ { \\pm } ) x _ { j } ^ { + } \\leq b _ { i } ^ { - } , \\ i = 1 , \\dots , m , \\\\ j \\in A _ { 1 } & & j \\in A _ { 2 } \\\\ x _ { j } ^ { - } \\geq 0 , \\ \\text {for } j \\in A _ { 1 } , \\\\ x _ { j } ^ { + } \\geq 0 , \\ \\text {for } j \\in A _ { 2 } . \\\\ \\intertext { s . t. } \\text {by solving the first sub-model and using its optimal solutions, the second sub-model}",
      "image_path": "visuals/equations/equation_026.png",
      "number": null
    },
    {
      "id": "eq-027",
      "page": 14,
      "bbox": [
        61.4564840536418,
        245.3397275381024,
        388.32686567322185,
        371.4064323725937
      ],
      "latex": "c a n b e \\text { formatted as follows:} \\\\ \\max Z ^ { + } = \\sum _ { j \\in A _ { 1 } } c _ { j } ^ { + } x _ { j } ^ { + } + \\sum _ { j \\in A _ { 2 } } c _ { j } ^ { + } x _ { j } ^ { - } \\\\ s . t . \\sum _ { j \\in A _ { 1 } } | a _ { i j } ^ { \\pm } | ^ { - } s i g n ( a _ { i j } ^ { \\pm } ) x _ { j } ^ { + } + \\sum _ { j \\in A _ { 2 } } | a _ { i j } ^ { \\pm } | ^ { + } s i g n ( a _ { i j } ^ { \\pm } ) x _ { j } ^ { - } \\leq b _ { i } ^ { + } , \\ i = 1 , \\dots , m , \\\\ x _ { j } ^ { + } \\geq x _ { j } ^ { - } , \\quad \\text {for } j \\in A _ { 1 } , \\\\ 0 \\leq x _ { j } ^ { - } \\leq x _ { j } ^ { + } , \\ \\text { for } j \\in A _ { 2 } , \\\\ x _ { j } ^ { + } \\geq 0 , \\quad \\text {for } j \\in A _ { 1 } , \\\\ \\sum _ { j \\in B _ { 2 } } ( | a _ { \\delta j } ^ { \\pm } | ^ { - } x _ { j } ^ { + } - | a _ { \\delta j } ^ { \\pm } | ^ { + } x _ { j _ { n } } ^ { - } ) + \\sum _ { j \\in B _ { 4 } } ( | a _ { \\delta j } ^ { \\pm } | ^ { x _ { j } ^ { - } } - | a _ { \\delta j } ^ { \\pm } | ^ { - } x _ { j _ { n } } ^ { + } ) \\geq 0 , \\\\ \\text {where } A _ { j } , \\ j = 1 , 2 \\text { and } B _ { j } , \\ j = 2 , 4 \\text { are defined in the } S e c t s . \\ 3 . 2 \\text { and } 3 . 3 , \\, \\text { respectively}",
      "image_path": "visuals/equations/equation_027.png",
      "number": null
    },
    {
      "id": "eq-028",
      "page": 15,
      "bbox": [
        61.45543506095409,
        408.3885098871024,
        388.32686567322185,
        517.9009392085937
      ],
      "latex": "second \\, \\text {sub-model} \\, \\text { can be expressed as follows:} \\\\ \\min Z ^ { - } & = \\sum _ { j \\in A _ { 1 } } c _ { j } ^ { - } x _ { j } ^ { - } + \\sum _ { j \\in A _ { 2 } } c _ { j } ^ { - } x _ { j } ^ { + } \\\\ s . t . & \\quad \\sum _ { j \\in A _ { 1 } } | a _ { i j } ^ { \\pm } | ^ { + } s i g n ( a _ { i j } ^ { \\pm } ) x _ { j } ^ { - } + \\sum _ { j \\in A _ { 2 } } | a _ { i j } ^ { \\pm } | ^ { - } s i g n ( a _ { i j } ^ { \\pm } ) x _ { j } ^ { + } \\geq b _ { i } ^ { - } , \\ \\ i = 1 , \\dots , m , \\\\ & \\quad 0 \\leq x _ { j } ^ { - } \\leq x _ { j _ { m } } ^ { + } , \\ \\text { for } j \\in A _ { 1 } , \\\\ & \\quad x _ { j } ^ { + } \\geq x _ { j _ { m } } ^ { - } , \\quad \\text {for } j \\in A _ { 2 } , \\\\ & \\sum _ { j \\in B _ { 2 } } ( - | a _ { \\delta j } ^ { \\pm } | ^ { + } x _ { j } ^ { - } - | a _ { \\delta j } ^ { \\pm } | ^ { - } x _ { j _ { m } } ^ { + } ) + \\sum _ { j \\in B _ { 4 } } ( | a _ { \\delta j } ^ { \\pm } | ^ { - } x _ { j } ^ { + } - | a _ { \\delta j } ^ { \\pm } | ^ { + } x _ { j _ { m } } ^ { - } ) \\leq 0 , \\\\ \\text {where } A _ { j } , \\ \\ j = 1 , 2 \\text { and } B _ { j } , \\ \\ j = 2 , 4 \\text { are defined in the } \\text { Segs. } 3 . 2 \\text { and } 3 . 3 , \\ \\text { respectively}",
      "image_path": "visuals/equations/equation_028.png",
      "number": null
    },
    {
      "id": "eq-029",
      "page": 16,
      "bbox": [
        96.9449,
        543.0908109121024,
        388.32693126302297,
        565.5796501465937
      ],
      "latex": "\\sum _ { j \\in B _ { 1 } } ( | a _ { \\delta j } ^ { \\pm } | ^ { - } x _ { j } ^ { + } - | a _ { \\delta j } ^ { \\pm } | ^ { + } x _ { j \\sigma \\mu } ^ { - } ) + \\sum _ { j \\in B _ { 3 } } - ( | a _ { \\delta j } ^ { \\pm } | ^ { + } x _ { j } ^ { - } - | a _ { \\delta j } ^ { \\pm } | ^ { - } x _ { j \\sigma \\mu } ^ { + } ) \\leq 0 ,",
      "image_path": "visuals/equations/equation_029.png",
      "number": null
    },
    {
      "id": "eq-030",
      "page": 16,
      "bbox": [
        117.694503784,
        345.17592443710237,
        388.32642151451864,
        367.83483813459367
      ],
      "latex": "\\sum _ { j \\in A _ { 1 } } | a _ { \\delta j } ^ { \\pm } | ^ { - } s i g n ( a _ { \\delta j } ^ { \\pm } ) x _ { j } ^ { + } + \\sum _ { j \\in A _ { 2 } } | a _ { \\delta j } ^ { \\pm } | ^ { + } s i g n ( a _ { \\delta j } ^ { \\pm } ) x _ { j } ^ { - } \\geq b _ { \\delta } ^ { - } ,",
      "image_path": "visuals/equations/equation_030.png",
      "number": null
    },
    {
      "id": "eq-031",
      "page": 16,
      "bbox": [
        117.694503784,
        222.54912390010242,
        388.32642151451864,
        245.20814440859368
      ],
      "latex": "\\sum _ { j \\in A _ { 1 } } | a _ { \\delta j } ^ { \\pm } | ^ { - } s i g n ( a _ { \\delta j } ^ { \\pm } ) x _ { j } ^ { + } + \\sum _ { j \\in A _ { 2 } } | a _ { \\delta j } ^ { \\pm } | ^ { + } s i g n ( a _ { \\delta j } ^ { \\pm } ) x _ { j } ^ { - } \\leq b _ { \\delta } ^ { - } ,",
      "image_path": "visuals/equations/equation_031.png",
      "number": null
    },
    {
      "id": "eq-032",
      "page": 16,
      "bbox": [
        59.81048986311381,
        79.42091516821893,
        388.3257332468131,
        159.14823840859367
      ],
      "latex": "\\text {method as follows.} \\\\ \\max & Z ^ { - } = \\sum _ { j \\in A _ { 1 } } c _ { j } ^ { - } x _ { j } ^ { - } + \\sum _ { j \\in A _ { 2 } } c _ { j } ^ { - } x _ { j } ^ { + } \\\\ & s . t . \\quad \\sum _ { j \\in A _ { 1 } } | a _ { i j } ^ { + } | ^ { * } s i g n ( a _ { i j } ^ { + } ) x _ { j } ^ { - } + \\sum _ { j \\in A _ { 2 } } | a _ { i j } ^ { + } | ^ { * } s i g n ( a _ { i j } ^ { + } ) x _ { j } ^ { + } \\leq b _ { i } ^ { + } , \\ i = 1 , \\dots , m , \\quad ( 2 2 ) \\\\ & x _ { j } ^ { - } \\geq 0 , \\ \\text {for } j \\in A _ { 1 } , \\\\ & x _ { j } ^ { + } \\geq 0 , \\ \\text {for } j \\in A _ { 2 } .",
      "image_path": "visuals/equations/equation_032.png",
      "number": null
    },
    {
      "id": "eq-033",
      "page": 17,
      "bbox": [
        62.98270934418255,
        273.0625211171024,
        388.3267201882146,
        409.16393969759366
      ],
      "latex": "2 \\text { second sub-model of ISOM-2 method can be summarized as follows:} \\\\ \\max Z ^ { + } = \\sum _ { j \\in A _ { j } } c _ { j } ^ { + } x _ { j } ^ { + } + \\sum _ { j \\in A _ { j } } c _ { j } ^ { + } x _ { j } ^ { - } \\\\ s . t. \\sum _ { j \\in A _ { i } } | a _ { i j } ^ { + } | ^ { - } s i g n ( a _ { i j } ^ { + } ) x _ { j } ^ { + } + \\sum _ { j \\in A _ { i j } } | a _ { i j } ^ { + } | ^ { + } s i g n ( a _ { i j } ^ { + } ) x _ { j } ^ { - } \\geq b _ { i } ^ { - } , \\text { for } i \\in D _ { 2 } , \\\\ \\sum _ { j \\in A _ { i } } | a _ { i j } ^ { + } | ^ { - } s i g n ( a _ { i j } ^ { + } ) x _ { j } ^ { + } + \\sum _ { j \\in A _ { i j } } | a _ { i j } ^ { + } | ^ { + } s i g n ( a _ { i j } ^ { + } ) x _ { j } ^ { - } \\leq b _ { i } ^ { - } , \\text { for } i \\in D _ { 1 } , \\\\ j e A _ { 1 } \\\\ x _ { j } ^ { + } \\geq x _ { j _ { 0 } } ^ { - } , \\text { for } j \\in A _ { 1 } , \\\\ 0 \\leq x _ { j } ^ { - } \\leq x _ { j _ { 0 } } ^ { + } , \\text { for } j \\in A _ { 2 } , \\\\ \\sum _ { j \\in B _ { i } } ( | a _ { i j } ^ { + } | ^ { - } x _ { j } ^ { + } - | a _ { i j } ^ { + } | ^ { + } x _ { j } ^ { - } ) + \\sum _ { j \\in B _ { 3 } } ( | a _ { i j } ^ { + } | ^ { + } x _ { j } ^ { - } - | a _ { i j } ^ { + } | ^ { - } x _ { j } ^ { + } ) \\leq 0 . \\\\ \\text {The last constraint of model (23) is an extra constraint to ensure that solution space}",
      "image_path": "visuals/equations/equation_033.png",
      "number": null
    },
    {
      "id": "eq-034",
      "page": 18,
      "bbox": [
        92.4661026,
        583.4561063221024,
        387.946902735769,
        607.5324699705938
      ],
      "latex": "( A ^ { - } ) _ { i } x = a _ { i } ^ { - } x _ { 1 } + \\dots + a _ { i n } ^ { - } x _ { n } & \\leq \\sum _ { j \\in B _ { 1 } } a _ { i j } ^ { - } x _ { j _ { o p t } } ^ { + } + \\sum _ { j \\in B _ { 2 } \\bigcup B _ { 3 } } a _ { i j } ^ { - } x _ { j _ { o p t } } ^ { - } , i = 1 , \\dots , m . \\\\",
      "image_path": "visuals/equations/equation_034.png",
      "number": null
    },
    {
      "id": "eq-035",
      "page": 18,
      "bbox": [
        140.03149414,
        254.7852578072467,
        388.3255460431524,
        309.7139997757293
      ],
      "latex": "\\max _ { \\ } & \\ Z = [ 3 , 3 . 5 ] _ { x _ { 1 } } - [ 1 , 1 . 2 ] _ { x _ { 2 } } \\\\ \\text {s.t.} ; [ 1 , 1 . 1 ] _ { x _ { 1 } } + [ 1 . 6 , 1 . 8 ] _ { x _ { 2 } } \\leq [ 1 1 . 6 , 1 2 ] \\\\ [ 3 , 4 ] _ { x _ { 1 } } - [ 2 , 3 ] _ { x _ { 2 } } \\leq [ 5 , 7 ] \\\\ x _ { 1 } , x _ { 2 } \\geq 0 .",
      "image_path": "visuals/equations/equation_035.png",
      "number": null
    },
    {
      "id": "eq-036",
      "page": 19,
      "bbox": [
        130.847198486,
        243.4466500192467,
        388.3261666391016,
        298.3751957397593
      ],
      "latex": "\\max _ { \\ } & \\ Z = [ 3 , 3 . 5 ] _ { x _ { 1 } } - [ 1 , 1 . 2 ] _ { x _ { 2 } } \\\\ s . t . [ 1 , 1 . 1 ] _ { x _ { 1 } } + [ 1 . 6 , 1 . 8 ] _ { x _ { 2 } } + x _ { 3 } = [ 1 1 . 6 , 1 2 ] \\\\ [ 3 , 4 ] _ { x _ { 1 } } - [ 2 , 3 ] _ { x _ { 2 } } + x _ { 4 } = [ 5 , 7 ] \\\\ x _ { 1 } , x _ { 2 } , x _ { 3 } , x _ { 4 } \\geq 0 .",
      "image_path": "visuals/equations/equation_036.png",
      "number": null
    },
    {
      "id": "eq-037",
      "page": 20,
      "bbox": [
        79.20081019738569,
        513.7016396472467,
        357.3605018872399,
        538.7527954651424
      ],
      "latex": "U = & \\{ ( x _ { 1 } , x _ { 2 } ) \\colon x _ { 1 } + 1 . 6 x _ { 2 } \\leq 1 2 , \\ 3 x _ { 1 } - 3 x _ { 2 } \\leq 7 , \\ 1 . 1 x _ { 1 } + 1 . 8 x _ { 2 } \\geq 1 1 . 6 , \\\\ & 4 x _ { 1 } - 2 x _ { 2 } \\geq 5 , \\ x _ { 1 } , x _ { 2 } \\geq 0 \\} .",
      "image_path": "visuals/equations/equation_037.png",
      "number": null
    }
  ],
  "references": [
    {
      "id": "ref-1",
      "key": "1",
      "raw": "Allahdadi M, Mishmast Nehi H (2013) The optimal solutions set of the interval linear programming problems. Optim Lett 7:893-1911",
      "page": 24,
      "authors": null,
      "title": null,
      "venue": null,
      "year": null
    },
    {
      "id": "ref-2",
      "key": "2",
      "raw": "Allahdadi M, Mishmast Nehi H (2015) The optimal value bounds of the objective function in the interval linear programming problem. Chiang Mai J Sci 42(2):501-511",
      "page": 24,
      "authors": null,
      "title": null,
      "venue": null,
      "year": null
    },
    {
      "id": "ref-3",
      "key": "3",
      "raw": "Allahdadi M, Mishmast Nehi H, Ashayerinasab HA, Javanmard M (2016) Improving the modified interval linear programming method by new techniques. Inf Sci 339:224-236",
      "page": 24,
      "authors": null,
      "title": null,
      "venue": null,
      "year": null
    },
    {
      "id": "ref-4",
      "key": "4",
      "raw": "Ashayerinasab HA, Mishmast Nehi H, Allahdadi M (2018) Solving the interval linear programming problem: a new algorithm for a general case. Expt Syst Appl 93:39-49",
      "page": 24,
      "authors": null,
      "title": null,
      "venue": null,
      "year": null
    },
    {
      "id": "ref-5",
      "key": "5",
      "raw": "Beeck H (1978) Linear programming with inexact data. Technical report TUM-ISU-7830, Technical University of Munich, Munich",
      "page": 24,
      "authors": null,
      "title": null,
      "venue": null,
      "year": null
    },
    {
      "id": "ref-6",
      "key": "6",
      "raw": "Cai Y, Huang G, Nie X, Li Y, Tan Q (2007) Municipal solid waste management under uncertainty: a mixed interval parameter fuzzy-stochastic robust programming approach. Environ Eng Sci 24:338-352",
      "page": 24,
      "authors": null,
      "title": null,
      "venue": null,
      "year": null
    },
    {
      "id": "ref-7",
      "key": "7",
      "raw": "Chinneck JW, Ramadan K (2000) Linear programming with interval coefficients. J Oper Res Soc 51:209-220",
      "page": 24,
      "authors": null,
      "title": null,
      "venue": null,
      "year": null
    },
    {
      "id": "ref-8",
      "key": "8",
      "raw": "Fan YR, Huang GH (2012) A robust two-step method for solving interval linear programming problems within an environmental management context. J Environ Inf 19:1-12",
      "page": 24,
      "authors": null,
      "title": null,
      "venue": null,
      "year": null
    },
    {
      "id": "ref-9",
      "key": "9",
      "raw": "Guo P, Huang GH (2009a) Inexact fuzzy-chance-constrained two-stage mixed integer programming approach for long-term planning of municipal solid waste management Part A: methodology. J Environ Manag 91:461-470",
      "page": 24,
      "authors": null,
      "title": null,
      "venue": null,
      "year": null
    },
    {
      "id": "ref-10",
      "key": "10",
      "raw": "Guo P, Huang GH (2009b) Inexact fuzzy-chance-constrained two-stage mixed integer programming approach for long-term planning of municipal solid waste management Part B: case study. J Environ Manag 91:441-460",
      "page": 24,
      "authors": null,
      "title": null,
      "venue": null,
      "year": null
    },
    {
      "id": "ref-11",
      "key": "11",
      "raw": "He L, Huang GH, Zeng GM, Lu HW (2009) An interval mixed-integer semi-infinite programming method for municipal solid waste management. J Air Wast Manag Assoc 59:236-246",
      "page": 24,
      "authors": null,
      "title": null,
      "venue": null,
      "year": null
    },
    {
      "id": "ref-12",
      "key": "12",
      "raw": "Hladik M (2014) How to determine basis stability in interval linear programming. Optim Lett 8:375-389",
      "page": 24,
      "authors": null,
      "title": null,
      "venue": null,
      "year": null
    },
    {
      "id": "ref-13",
      "key": "13",
      "raw": "Huang GH (1996) An interval parameter water quality management model. Eng Optim 26:79-103",
      "page": 24,
      "authors": null,
      "title": null,
      "venue": null,
      "year": null
    },
    {
      "id": "ref-14",
      "key": "14",
      "raw": "Huang GH, Cao MF (2011) Analysis of solution methods for interval linear programming. J Environ Inf 17:54-64",
      "page": 24,
      "authors": null,
      "title": null,
      "venue": null,
      "year": null
    },
    {
      "id": "ref-15",
      "key": "15",
      "raw": "Huang GH, Moore RD (1993) Grey linear programming, its solving approach, and its application. Int J Syst Sci 24:159-172",
      "page": 24,
      "authors": null,
      "title": null,
      "venue": null,
      "year": null
    },
    {
      "id": "ref-16",
      "key": "16",
      "raw": "Huang GH, Baetz BW, Patry GG (1994) Capacity planning for solid waste management systems under uncertainty. Civil Eng Syst 11:43-73",
      "page": 24,
      "authors": null,
      "title": null,
      "venue": null,
      "year": null
    },
    {
      "id": "ref-17",
      "key": "17",
      "raw": "Huang GH, Baetz BW, Patry GG (1995) Grey integer programming: an application to waste management planning under uncertainty. Eur J Oper Res 83:594-620",
      "page": 24,
      "authors": null,
      "title": null,
      "venue": null,
      "year": null
    },
    {
      "id": "ref-18",
      "key": "18",
      "raw": "Jansson C (1988) A self-validating method for solving linear programming problems with interval input data. In: Kulisch, U., Stetter, H.J. (eds.) Scientific computation with automatic result verification. Comput Suppl 6:33-45",
      "page": 24,
      "authors": null,
      "title": null,
      "venue": null,
      "year": null
    },
    {
      "id": "ref-19",
      "key": "19",
      "raw": "Jansson C, Rump SM (1991) Rigorous solution of linear programming problems with uncertain data. Z Oper Res 35(2):87-111",
      "page": 24,
      "authors": null,
      "title": null,
      "venue": null,
      "year": null
    },
    {
      "id": "ref-20",
      "key": "20",
      "raw": "Konickova J (2001) Sufficient condition of basis stability of an interval linear programming problem. ZAMM Z Angew Math Mech 81(3):677-678",
      "page": 24,
      "authors": null,
      "title": null,
      "venue": null,
      "year": null
    },
    {
      "id": "ref-21",
      "key": "21",
      "raw": "Lu HW, Huang GH, Liu L, He L (2008) An interval-parameter fuzzy-stochastic programming approach for air quality management under uncertainty. Environ Eng Sci 25:895-909",
      "page": 24,
      "authors": null,
      "title": null,
      "venue": null,
      "year": null
    }
  ],
  "code_blocks": [],
  "quality": {
    "status": "ok",
    "gates": {
      "canonical_non_empty": true,
      "has_references_section": true,
      "raster_page_count_ok": true,
      "paper_md_exists": true,
      "context_packet_valid": true
    }
  },
  "evidence_index": {
    "original_pdf": "debug/original.pdf",
    "pages_dir": "pages/",
    "page_paths": [
      "pages/page_0001.png",
      "pages/page_0002.png",
      "pages/page_0003.png",
      "pages/page_0004.png",
      "pages/page_0005.png",
      "pages/page_0006.png",
      "pages/page_0007.png",
      "pages/page_0008.png",
      "pages/page_0009.png",
      "pages/page_0010.png",
      "pages/page_0011.png",
      "pages/page_0012.png",
      "pages/page_0013.png",
      "pages/page_0014.png",
      "pages/page_0015.png",
      "pages/page_0016.png",
      "pages/page_0017.png",
      "pages/page_0018.png",
      "pages/page_0019.png",
      "pages/page_0020.png",
      "pages/page_0021.png",
      "pages/page_0022.png",
      "pages/page_0023.png",
      "pages/page_0024.png",
      "pages/page_0025.png"
    ]
  }
}
